CHANGES.txt
LICENSE.txt
MANIFEST.in
README.txt
setup.py
cacheable/__init__.py
cacheable.egg-info/PKG-INFO
cacheable.egg-info/SOURCES.txt
cacheable.egg-info/dependency_links.txt
cacheable.egg-info/top_level.txt
cacheable/adapter/DictAdapter.py
cacheable/adapter/PeeweeAdapter.py
cacheable/adapter/__init__.py